detokenizer/Detokenizer.py
detokenizer/Scanner.py
detokenizer/__init__.py
detokenizer/__main__.py
detokenizer-1.0.0rc8.dist-info/LICENSE
detokenizer-1.0.0rc8.dist-info/METADATA
detokenizer-1.0.0rc8.dist-info/WHEEL
detokenizer-1.0.0rc8.dist-info/entry_points.txt
detokenizer-1.0.0rc8.dist-info/top_level.txt
detokenizer-1.0.0rc8.dist-info/RECORD
