Metadata-Version: 2.1
Name: detokenizer
Version: 1.0.0rc8
Summary: Python command line for property injection.
Home-page: https://github.com/mmuellersk/detokenizer.git
Author: Matthias Müller
Author-email: mmueller.persoanl@gmail.com
License-File: LICENSE
Requires-Dist: pyyaml
